{"cameraMode":{"drawMode":0,"name":"Shaded","section":"Shading Mode"},"sceneLighting":true,"audioPlay":false,"sceneViewState":{"showFog":true,"showMaterialUpdate":false,"showSkybox":true,"showFlares":true,"showImageEffects":true,"showParticleSystems":true},"in2DMode":false,"pivot":{"x":-8362.6943359375,"y":257.4610900878906,"z":5051.9931640625},"rotation":{"x":0.034334294497966769,"y":-0.5579652786254883,"z":0.023107366636395456,"w":0.8288469314575195},"size":7482.1533203125,"orthographic":false}